dbt_docs/__init__.py
dbt_docs-0.0.1.dist-info/METADATA
dbt_docs-0.0.1.dist-info/WHEEL
dbt_docs-0.0.1.dist-info/RECORD
